torch2transformer/__init__.py
torch2transformer/config.py
torch2transformer/factory.py
torch2transformer/model.py
torch2transformer/version.py
torch2transformer-0.2.0.dist-info/licenses/LICENSE
torch2transformer-0.2.0.dist-info/METADATA
torch2transformer-0.2.0.dist-info/WHEEL
torch2transformer-0.2.0.dist-info/top_level.txt
torch2transformer-0.2.0.dist-info/RECORD
