Metadata-Version: 2.4
Name: torch2transformer
Version: 0.2.0
Summary: # torch2transformer
Author: Louis MAI
Project-URL: Homepage, https://github.com/longmaisg/torch2transformer
Project-URL: Repository, https://github.com/longmaisg/torch2transformer
Requires-Python: >=3.9
License-File: LICENSE
Requires-Dist: torch
Requires-Dist: transformers>=4.30
Dynamic: license-file
